core/__init__.py
core/array.py
examples/demo.py
mininumpy-0.1.2.dist-info/licenses/LICENSE
operations/__init__.py
operations/arithmetic.py
operations/stats.py
parallel/__init__.py
parallel/parallel.py
tests/test_basic.py
mininumpy-0.1.2.dist-info/METADATA
mininumpy-0.1.2.dist-info/WHEEL
mininumpy-0.1.2.dist-info/entry_points.txt
mininumpy-0.1.2.dist-info/top_level.txt
mininumpy-0.1.2.dist-info/RECORD
