Metadata-Version: 2.4
Name: mininumpy
Version: 0.1.2
Summary: A minimal implementation of NumPy's core functionality for educational purposes and lightweight applications
Home-page: https://github.com/fahad-678/mininumpy
Author: Fahad Haroon
Author-email: Fahad Haroon <fahadharoon678@gmail.com>
License-Expression: MIT
Project-URL: Bug Reports, https://github.com/fahad-678/mininumpy/issues
Project-URL: Source, https://github.com/fahad-678/mininumpy
Project-URL: Documentation, https://github.com/fahad-678/mininumpy/wiki
Keywords: numpy,array,parallel,computing,threading,multiprocessing,educational
Classifier: Development Status :: 3 - Alpha
Classifier: Intended Audience :: Developers
Classifier: Programming Language :: Python :: 3
Classifier: Programming Language :: Python :: 3.8
Classifier: Programming Language :: Python :: 3.9
Classifier: Programming Language :: Python :: 3.10
Classifier: Programming Language :: Python :: 3.11
Classifier: Programming Language :: Python :: 3.12
Classifier: Programming Language :: Python :: 3.13
Requires-Python: >=3.8
License-File: LICENSE
Provides-Extra: dev
Requires-Dist: pytest>=6.0; extra == "dev"
Requires-Dist: pytest-cov>=2.0; extra == "dev"
Requires-Dist: black>=21.0; extra == "dev"
Requires-Dist: flake8>=3.8; extra == "dev"
Provides-Extra: plotting
Requires-Dist: matplotlib>=3.3.0; extra == "plotting"
Provides-Extra: benchmarking
Requires-Dist: matplotlib>=3.3.0; extra == "benchmarking"
Requires-Dist: numpy>=1.19.0; extra == "benchmarking"
Dynamic: author
Dynamic: home-page
Dynamic: license-file
Dynamic: requires-python
